{
  "title": "Truck Loading Crude Oil",
  "section": [
    {
      "id": 1,
      "title": "Plan",
      "topic": [
        {
          "id": 1,
          "title": "Resources: materials, documents and equipments",
          "page": []
        },
        {
          "id": 2,
          "title": "Environmental, health, safety and security requirements",
          "page": []
        },
        {
          "id": 3,
          "title": "Training",
          "page": []
        },
        {
          "id": 4,
          "title": "Roles and responsibilities",
          "page": [
            {
              "id": "1",
              "title": "Operator",
              "html_url": "",
              "data_url": ""
            },
            {
              "id": "2",
              "title": "Driver",
              "html_url": "",
              "data_url": ""
            }
          ]
        }
      ]
    },
    {
      "id": 2,
      "title": "Do & Check",
      "topic": [
        {
          "id": 1,
          "title": "Procedure",
          "page": []
        },
        {
          "id": 2,
          "title": "Completion/Shutdown",
          "page": []
        },
        {
          "id": 3,
          "title": "Emergency Operators",
          "page": []
        },
        {
          "id": 4,
          "title": "Emergency Shutdown",
          "page": []
        }
      ]
    },
    {
      "id": 3,
      "title": "Check & Act",
      "topic": [
        {
          "id": 1,
          "title": "Reviewing the SOP",
          "page": []
        }
      ]
    }
  ]
}